Workbook

Sheet Supuestos
B2: Proyecto Café · Supuestos del modelo
B3: Verde importado (comprado a importador local, en pesos) + tueste tercerizado · 6 meses · a precios de jun-2026
B5: ⚠ Modelo ILUSTRATIVO. Las celdas en amarillo NO están validadas (averiguaciones #1, #2 y #3). Sirve para ver la ESTRUCTURA y el punto de equilibrio, no como pronóstico de ganancias. Cambiá los valores azules y todo recalcula.
B9: PARÁMETRO | C9: VALOR | D9: UNIDAD | E9: NOTA / FUENTE
B10: Tipo de cambio (ARS/USD) | C10: 1430 | D10: ARS/USD | E10: MEP/blue al 1/6/2026 (~$1.430)
B11: Café verde importado (local) | C11: 9 | D11: USD/kg | E11: SUPUESTO — averiguación #2
B12: Merma de tueste | C12: 0.17 | D12: % | E12: Verde→tostado pierde ~15-18% del peso
B13: Maquila (tueste tercerizado) | C13: 4500 | D13: ARS/kg tostado | E13: SUPUESTO — averiguación #1
B14: Packaging doypack 250g c/válvula | C14: 550 | D14: ARS/unidad | E14: Estimado
B15: Etiqueta 250g | C15: 200 | D15: ARS/unidad | E15: Estimado
B16: Packaging bulk 1kg (B2B) | C16: 1100 | D16: ARS/unidad | E16: Estimado
B17: Logística B2C absorbida | C17: 1500 | D17: ARS/u 250g | E17: Parte del envío que paga la marca
B18: Logística B2B | C18: 1200 | D18: ARS/kg | E18: Entrega a cafeterías
B19: Comisión medios de pago (B2C) | C19: 0.065 | D19: % | E19: MercadoPago/Tiendanube ~6,5%
B20: Comisión B2B | C20: 0 | D20: % | E20: Transferencia
B21: PVP online 250g | C21: 22000 | D21: ARS/unidad | E21: Góndola specialty 250g: $19.100–$23.400 (jun-2026)
... B26: Marca + diseño + INPI (inicial) | C26: 150000 | D26: ARS una vez | E26: Mes 1

Sheet Unit Economics
B2: Economía unitaria
B3: Costo y margen de una bolsa de 250 g (online) y de un kilo mayorista (cafeterías)
B5: BOLSA 250 g · Venta online (B2C)
B6: Ingreso (PVP) | C6: =Supuestos!$C$21 -> 22000
B7: Café verde necesario (kg) | C7: =0.25/(1-Supuestos!$C$12) -> 0.30120482
B8: Costo café verde | C8: =C7*Supuestos!$C$10*Supuestos!$C$11 -> 3876.506
B9: Maquila (tueste) | C9: =0.25*Supuestos!$C$13 -> 1125
B10: Packaging + etiqueta | C10: =Supuestos!$C$14+Supuestos!$C$15 -> 750
B11: Logística | C11: =Supuestos!$C$17 -> 1500
B12: Comisión medios de pago | C12: =C6*Supuestos!$C$19 -> 1430
B13: COGS total | C13: =SUM(C8:C12) -> 8681.506
B14: Margen bruto $ | C14: =C6-C13 -> 13318.494
B15: Margen bruto % | C15: =C14/C6 -> 0.60538609
B17: KILO mayorista · Cafeterías (B2B)
B18: Ingreso (precio/kg) | C18: =Supuestos!$C$22 -> 48000
B19: Café verde necesario (kg) | C19: =1/(1-Supuestos!$C$12) -> 1.2048193
B20: Costo café verde | C20: =C19*Supuestos!$C$10*Supuestos!$C$11 -> 15506.024
B21: Maquila (tueste) | C21: =1*Supuestos!$C$13 -> 4500
B22: Packaging bulk | C22: =Supuestos!$C$16 -> 1100
B23: Logística B2B | C23: =Supuestos!$C$18 -> 1200
B24: Comisión | C24: =C18*Supuestos!$C$20 -> 0
B25: COGS total | C25: =SUM(C20:C24) -> 22306.024
B26: Margen bruto $ | C26: =C18-C25 -> 25693.976
B27: Margen bruto % | C27: =C26/C18 -> 0.53529116

Sheet Proyección 6M
B2: Proyección a 6 meses
B3: Ramp-up de ventas a precios de hoy. Resultado ANTES de pagarse sueldo los socios y de impuestos más allá del monotributo.
B5: CONCEPTO | C5: Mes 1 | D5: Mes 2 | E5: Mes 3 | F5: Mes 4 | G5: Mes 5 | H5: Mes 6 | I5: TOTAL
B6: Bolsas 250g vendidas | C6: 10 | D6: 30 | E6: 50 | F6: 70 | G6: 90 | H6: 110 | I6: =SUM(C6:H6) -> 360
B7: Kg mayorista vendidos | C7: 0 | D7: 5 | E7: 10 | F7: 15 | G7: 20 | H7: 25 | I7: =SUM(C7:H7) -> 75
B9: INGRESOS
B10: Ingresos B2C (online) | C10: =C6*Supuestos!$C$21 -> 220000 | D10: =D6*Supuestos!$C$21 -> 660000 | E10: =E6*Supuestos!$C$21 -> 1100000 | F10: =F6*Supuestos!$C$21 -> 1540000 | G10: =G6*Supuestos!$C$21 -> 1980000 | H10: =H6*Supuestos!$C$21 -> 2420000 | I10: =SUM(C10:H10) -> 7920000
B11: Ingresos B2B (cafeterías) | C11: =C7*Supuestos!$C$22 -> 0 | D11: =D7*Supuestos!$C$22 -> 240000 | E11: =E7*Supuestos!$C$22 -> 480000 | F11: =F7*Supuestos!$C$22 -> 720000 | G11: =G7*Supuestos!$C$22 -> 960000 | H11: =H7*Supuestos!$C$22 -> 1200000 | I11: =SUM(C11:H11) -> 3600000
B12: Ingresos totales | C12: =C10+C11 -> 220000 | D12: =D10+D11 -> 900000 | E12: =E10+E11 -> 1580000 | F12: =F10+F11 -> 2260000 | G12: =G10+G11 -> 2940000 | H12: =H10+H11 -> 3620000 | I12: =SUM(C12:H12) -> 11520000
B14: COSTOS VARIABLES (COGS)
B15: COGS B2C | C15: =C6*'Unit Economics'!$C$13 -> 86815.06 | D15: =D6*'Unit Economics'!$C$13 -> 260445.18 | E15: =E6*'Unit Economics'!$C$13 -> 434075.3 | F15: =F6*'Unit Economics'!$C$13 -> 607705.42 | G15: =G6*'Unit Economics'!$C$13 -> 781335.54 | H15: =H6*'Unit Economics'!$C$13 -> 954965.66 | I15: =SUM(C15:H15) -> 3125342.2
B16: COGS B2B | C16: =C7*'Unit Economics'!$C$25 -> 0 | D16: =D7*'Unit Economics'!$C$25 -> 111530.12 | E16: =E7*'Unit Economics'!$C$25 -> 223060.24 | F16: =F7*'Unit Economics'!$C$25 -> 334590.36 | G16: =G7*'Unit Economics'!$C$25 -> 446120.48 | H16: =H7*'Unit Economics'!$C$25 -> 557650.6 | I16: =SUM(C16:H16) -> 1672951.8
B17: COGS total | C17: =C15+C16 -> 86815.06 | D17: =D15+D16 -> 371975.3 | E17: =E15+E16 -> 657135.54 | F17: =F15+F16 -> 942295.78 | G17: =G15+G16 -> 1227456 | H17: =H15+H16 -> 1512616.3 | I17: =SUM(C17:H17) -> 4798294
B18: Margen bruto | C18: =C12-C17 -> 133184.94 | D18: =D12-D17 -> 528024.7 | E18: =E12-E17 -> 922864.46 | F18: =F12-F17 -> 1317704.2 | G18: =G12-G17 -> 1712544 | H18: =H12-H17 -> 2107383.7 | I18: =SUM(C18:H18) -> 6721706
B19: Margen bruto % | C19: =IF(C12=0,0,C18/C12) -> 0.60538609 | D19: =IF(D12=0,0,D18/D12) -> 0.58669411 | E19: =IF(E12=0,0,E18/E12) -> 0.58409143 | F19: =IF(F12=0,0,F18/F12) -> 0.58305496 | G19: =IF(G12=0,0,G18/G12) -> 0.58249795 | H19: =IF(H12=0,0,H18/H12) -> 0.5821502 | I19: =IF(I17=0,0,I18/I17) -> 1.4008533
B21: COSTOS FIJOS
B22: Monotributo | C22: =Supuestos!$C$23 -> 35000 | D22: =Supuestos!$C$23 -> 35000 | E22: =Supuestos!$C$23 -> 35000 | F22: =Supuestos!$C$23 -> 35000 | G22: =Supuestos!$C$23 -> 35000 | H22: =Supuestos!$C$23 -> 35000 | I22: =SUM(C22:H22) -> 210000
B23: Tienda online | C23: =Supuestos!$C$24 -> 12000 | D23: =Supuestos!$C$24 -> 12000 | E23: =Supuestos!$C$24 -> 12000 | F23: =Supuestos!$C$24 -> 12000 | G23: =Supuestos!$C$24 -> 12000 | H23: =Supuestos!$C$24 -> 12000 | I23: =SUM(C23:H23) -> 72000
B24: Marketing / IG | C24: =Supuestos!$C$25 -> 25000 | D24: =Supuestos!$C$25 -> 25000 | E24: =Supuestos!$C$25 -> 25000 | F24: =Supuestos!$C$25 -> 25000 | G24: =Supuestos!$C$25 -> 25000 | H24: =Supuestos!$C$25 -> 25000 | I24: =SUM(C24:H24) -> 150000
B25: Setup inicial (marca/INPI) | C25: =Supuestos!$C$26 -> 150000 | D25: 0 | E25: 0 | F25: 0 | G25: 0 | H25: 0 | I25: =SUM(C25:H25) -> 150000
B26: Total costos fijos | C26: =SUM(C22:C25) -> 222000 | D26: =SUM(D22:D25) -> 72000 | E26: =SUM(E22:E25) -> 72000 | F26: =SUM(F22:F25) -> 72000 | G26: =SUM(G22:G25) -> 72000 | H26: =SUM(H22:H25) -> 72000 | I26: =SUM(C26:H26) -> 582000
B28: RESULTADO OPERATIVO | C28: =C18-C26 -> -88815.06 | D28: =D18-D26 -> 456024.7 | E28: =E18-E26 -> 850864.46 | F28: =F18-F26 -> 1245704.2 | G28: =G18-G26 -> 1640544 | H28: =H18-H26 -> 2035383.7 | I28: =SUM(C28:H28) -> 6139706
B29: Resultado acumulado | C29: =C28 -> -88815.06 | D29: =C29+D28 -> 367209.64 | E29: =D29+E28 -> 1218074.1 | F29: =E29+F28 -> 2463778.3 | G29: =F29+G28 -> 4104322.3 | H29: =G29+H28 -> 6139706 | I29: =H29 -> 6139706
B31: Nota: el COGS se imputa en el mes de venta (simplificación). En caja real, la compra de verde + maquila se desembolsa ANTES de cobrar: prevé capital de trabajo para financiar el primer lote.

Sheet Equilibrio y Sensib.
B2: Punto de equilibrio y sensibilidad
B4: Punto de equilibrio mensual (solo canal B2C)
B5: Costos fijos mensuales (sin setup) | C5: =Supuestos!$C$23+Supuestos!$C$24+Supuestos!$C$25 -> 72000 | E5: El equilibrio es bajísimo: este NO es un negocio de costos fijos. El costo está en lo variable (café) y el verdadero problema es el VOLUMEN de venta, no llegar a cubrir fijos. La pregunta que el modelo no responde: ¿vendés las bolsas?
B6: Margen bruto por bolsa 250g | C6: ='Unit Economics'!$C$14 -> 13318.494
B7: Bolsas/mes para cubrir fijos | C7: =C5/C6 -> 5.4060166
B10: Margen bruto % de la bolsa 250g según costo del verde (filas) y PVP (columnas)
B11: verde \ PVP | C11: 18000 | D11: 20000 | E11: 22000 | F11: 24000 | G11: 26000
B12: 6 | C12: =(C$11-((0.25/(1-Supuestos!$C$12))*Supuestos!$C$10*$B12+0.25*Supuestos!$C$13+Supuestos!$C$14+Supuestos!$C$15+Supuestos!$C$17+C$11*Supuestos!$C$19))/C$11 -> 0.6039257 | D12: =(D$11-((0.25/(1-Supuestos!$C$12))*Supuestos!$C$10*$B12+0.25*Supuestos!$C$13+Supuestos!$C$14+Supuestos!$C$15+Supuestos!$C$17+D$11*Supuestos!$C$19))/D$11 -> 0.63703313 | E12: =(E$11-((0.25/(1-Supuestos!$C$12))*Supuestos!$C$10*$B12+0.25*Supuestos!$C$13+Supuestos!$C$14+Supuestos!$C$15+Supuestos!$C$17+E$11*Supuestos!$C$19))/E$11 -> 0.66412103 | F12: =(F$11-((0.25/(1-Supuestos!$C$12))*Supuestos!$C$10*$B12+0.25*Supuestos!$C$13+Supuestos!$C$14+Supuestos!$C$15+Supuestos!$C$17+F$11*Supuestos!$C$19))/F$11 -> 0.68669428 | G12: =(G$11-((0.25/(1-Supuestos!$C$12))*Supuestos!$C$10*$B12+0.25*Supuestos!$C$13+Supuestos!$C$14+Supuestos!$C$15+Supuestos!$C$17+G$11*Supuestos!$C$19))/G$11 -> 0.70579472
B13: 8 | C13: =(C$11-((0.25/(1-Supuestos!$C$12))*Supuestos!$C$10*$B13+0.25*Supuestos!$C$13+Supuestos!$C$14+Supuestos!$C$15+Supuestos!$C$17+C$11*Supuestos!$C$19))/C$11 -> 0.5560676 | D13: =(D$11-((0.25/(1-Supuestos!$C$12))*Supuestos!$C$10*$B13+0.25*Supuestos!$C$13+Supuestos!$C$14+Supuestos!$C$15+Supuestos!$C$17+D$11*Supuestos!$C$19))/D$11 -> 0.59396084 | E13: =(E$11-((0.25/(1-Supuestos!$C$12))*Supuestos!$C$10*$B13+0.25*Supuestos!$C$13+Supuestos!$C$14+Supuestos!$C$15+Supuestos!$C$17+E$11*Supuestos!$C$19))/E$11 -> 0.6249644 | F13: =(F$11-((0.25/(1-Supuestos!$C$12))*Supuestos!$C$10*$B13+0.25*Supuestos!$C$13+Supuestos!$C$14+Supuestos!$C$15+Supuestos!$C$17+F$11*Supuestos!$C$19))/F$11 -> 0.6508007 | G13: =(G$11-((0.25/(1-Supuestos!$C$12))*Supuestos!$C$10*$B13+0.25*Supuestos!$C$13+Supuestos!$C$14+Supuestos!$C$15+Supuestos!$C$17+G$11*Supuestos!$C$19))/G$11 -> 0.67266219
B14: 9 | C14: =(C$11-((0.25/(1-Supuestos!$C$12))*Supuestos!$C$10*$B14+0.25*Supuestos!$C$13+Supuestos!$C$14+Supuestos!$C$15+Supuestos!$C$17+C$11*Supuestos!$C$19))/C$11 -> 0.53213855 | D14: =(D$11-((0.25/(1-Supuestos!$C$12))*Supuestos!$C$10*$B14+0.25*Supuestos!$C$13+Supuestos!$C$14+Supuestos!$C$15+Supuestos!$C$17+D$11*Supuestos!$C$19))/D$11 -> 0.5724247 | E14: =(E$11-((0.25/(1-Supuestos!$C$12))*Supuestos!$C$10*$B14+0.25*Supuestos!$C$13+Supuestos!$C$14+Supuestos!$C$15+Supuestos!$C$17+E$11*Supuestos!$C$19))/E$11 -> 0.60538609 | F14: =(F$11-((0.25/(1-Supuestos!$C$12))*Supuestos!$C$10*$B14+0.25*Supuestos!$C$13+Supuestos!$C$14+Supuestos!$C$15+Supuestos!$C$17+F$11*Supuestos!$C$19))/F$11 -> 0.63285392 | G14: =(G$11-((0.25/(1-Supuestos!$C$12))*Supuestos!$C$10*$B14+0.25*Supuestos!$C$13+Supuestos!$C$14+Supuestos!$C$15+Supuestos!$C$17+G$11*Supuestos!$C$19))/G$11 -> 0.65609592
B15: 10 | C15: =(C$11-((0.25/(1-Supuestos!$C$12))*Supuestos!$C$10*$B15+0.25*Supuestos!$C$13+Supuestos!$C$14+Supuestos!$C$15+Supuestos!$C$17+C$11*Supuestos!$C$19))/C$11 -> 0.5082095 | D15: =(D$11-((0.25/(1-Supuestos!$C$12))*Supuestos!$C$10*$B15+0.25*Supuestos!$C$13+Supuestos!$C$14+Supuestos!$C$15+Supuestos!$C$17+D$11*Supuestos!$C$19))/D$11 -> 0.55088855 | E15: =(E$11-((0.25/(1-Supuestos!$C$12))*Supuestos!$C$10*$B15+0.25*Supuestos!$C$13+Supuestos!$C$14+Supuestos!$C$15+Supuestos!$C$17+E$11*Supuestos!$C$19))/E$11 -> 0.58580778 | F15: =(F$11-((0.25/(1-Supuestos!$C$12))*Supuestos!$C$10*$B15+0.25*Supuestos!$C$13+Supuestos!$C$14+Supuestos!$C$15+Supuestos!$C$17+F$11*Supuestos!$C$19))/F$11 -> 0.61490713 | G15: =(G$11-((0.25/(1-Supuestos!$C$12))*Supuestos!$C$10*$B15+0.25*Supuestos!$C$13+Supuestos!$C$14+Supuestos!$C$15+Supuestos!$C$17+G$11*Supuestos!$C$19))/G$11 -> 0.63952966
B16: 12 | C16: =(C$11-((0.25/(1-Supuestos!$C$12))*Supuestos!$C$10*$B16+0.25*Supuestos!$C$13+Supuestos!$C$14+Supuestos!$C$15+Supuestos!$C$17+C$11*Supuestos!$C$19))/C$11 -> 0.46035141 | D16: =(D$11-((0.25/(1-Supuestos!$C$12))*Supuestos!$C$10*$B16+0.25*Supuestos!$C$13+Supuestos!$C$14+Supuestos!$C$15+Supuestos!$C$17+D$11*Supuestos!$C$19))/D$11 -> 0.50781627 | E16: =(E$11-((0.25/(1-Supuestos!$C$12))*Supuestos!$C$10*$B16+0.25*Supuestos!$C$13+Supuestos!$C$14+Supuestos!$C$15+Supuestos!$C$17+E$11*Supuestos!$C$19))/E$11 -> 0.54665115 | F16: =(F$11-((0.25/(1-Supuestos!$C$12))*Supuestos!$C$10*$B16+0.25*Supuestos!$C$13+Supuestos!$C$14+Supuestos!$C$15+Supuestos!$C$17+F$11*Supuestos!$C$19))/F$11 -> 0.57901355 | G16: =(G$11-((0.25/(1-Supuestos!$C$12))*Supuestos!$C$10*$B16+0.25*Supuestos!$C$13+Supuestos!$C$14+Supuestos!$C$15+Supuestos!$C$17+G$11*Supuestos!$C$19))/G$11 -> 0.60639713
B17: 14 | C17: =(C$11-((0.25/(1-Supuestos!$C$12))*Supuestos!$C$10*$B17+0.25*Supuestos!$C$13+Supuestos!$C$14+Supuestos!$C$15+Supuestos!$C$17+C$11*Supuestos!$C$19))/C$11 -> 0.41249331 | D17: =(D$11-((0.25/(1-Supuestos!$C$12))*Supuestos!$C$10*$B17+0.25*Supuestos!$C$13+Supuestos!$C$14+Supuestos!$C$15+Supuestos!$C$17+D$11*Supuestos!$C$19))/D$11 -> 0.46474398 | E17: =(E$11-((0.25/(1-Supuestos!$C$12))*Supuestos!$C$10*$B17+0.25*Supuestos!$C$13+Supuestos!$C$14+Supuestos!$C$15+Supuestos!$C$17+E$11*Supuestos!$C$19))/E$11 -> 0.50749452 | F17: =(F$11-((0.25/(1-Supuestos!$C$12))*Supuestos!$C$10*$B17+0.25*Supuestos!$C$13+Supuestos!$C$14+Supuestos!$C$15+Supuestos!$C$17+F$11*Supuestos!$C$19))/F$11 -> 0.54311998 | G17: =(G$11-((0.25/(1-Supuestos!$C$12))*Supuestos!$C$10*$B17+0.25*Supuestos!$C$13+Supuestos!$C$14+Supuestos!$C$15+Supuestos!$C$17+G$11*Supuestos!$C$19))/G$11 -> 0.5732646
B19: Verde y PVP de hoy resaltados arriba. Si el verde te sale $14/kg en vez de $9, el margen se come ~12 puntos.
